Workbook

Sheet Sales Report
A1: Order ID | B1: Date | C1: Month | D1: Channel | E1: Address | F1: Customer | G1: Product | H1: Units | I1: Unit Price (USD) | J1: Gross Sales (USD) | K1: Discount % | L1: Net Sales (USD) | M1: Unit Cost (USD) | N1: COGS (USD) | O1: Gross Profit (USD) | P1: Status
A2: 20250001 | B2: 45658 | C2: Jan | D2: Online | E2: Maple Avenue 21 | F2: Brenda Alves | G2: E-book | H2: 24 | I2: 9.94 | J2: =H2*I2 -> 238.56 | K2: 0 | L2: =IF(P2="Returned",0,J2*(1-K2)) -> 238.56 | M2: 1 | N2: =IF(P2="Returned",0,H2*M2) -> 24 | O2: =L2-N2 -> 214.56 | P2: Completed
A3: =A2+1 -> 20250002 | B3: 45658 | C3: Jan | D3: Online | E3: Maple Avenue 235 | F3: Allison Hill | G3: Hardcover | H3: 18 | I3: 29.42 | J3: =H3*I3 -> 529.56 | K3: 0.03 | L3: =IF(P3="Returned",0,J3*(1-K3)) -> 0 | M3: 15 | N3: =IF(P3="Returned",0,H3*M3) -> 0 | O3: =L3-N3 -> 0 | P3: Returned
A4: =A3+1 -> 20250003 | B4: 45658 | C4: Jan | D4: Online | E4: Harbor Road 110 | F4: William Jennings | G4: Hardcover | H4: 9 | I4: 27.11 | J4: =H4*I4 -> 243.99 | K4: 0.05 | L4: =IF(P4="Returned",0,J4*(1-K4)) -> 231.7905 | M4: 15 | N4: =IF(P4="Returned",0,H4*M4) -> 135 | O4: =L4-N4 -> 96.7905 | P4: Completed
A5: =A4+1 -> 20250004 | B5: 45658 | C5: Jan | D5: Shop | E5: Lake View Road 111 | F5: Noah Rhodes | G5: E-book | H5: 24 | I5: 8.09 | J5: =H5*I5 -> 194.16 | K5: 0 | L5: =IF(P5="Returned",0,J5*(1-K5)) -> 194.16 | M5: 1 | N5: =IF(P5="Returned",0,H5*M5) -> 24 | O5: =L5-N5 -> 170.16 | P5: Completed
A6: =A5+1 -> 20250005 | B6: 45658 | C6: Jan | D6: Shop | E6: River Street 164 | F6: Angie Henderson | G6: Collector Edition | H6: 2 | I6: 46.23 | J6: =H6*I6 -> 92.46 | K6: 0.02 | L6: =IF(P6="Returned",0,J6*(1-K6)) -> 90.6108 | M6: 24 | N6: =IF(P6="Returned",0,H6*M6) -> 48 | O6: =L6-N6 -> 42.6108 | P6: Completed
A7: =A6+1 -> 20250006 | B7: 45658 | C7: Jan | D7: Delivery | E7: Green Lane 15 | F7: Daniel Wagner | G7: Hardcover | H7: 91 | I7: 28.21 | J7: =H7*I7 -> 2567.11 | K7: 0.08 | L7: =IF(P7="Returned",0,J7*(1-K7)) -> 2361.7412 | M7: 15 | N7: =IF(P7="Returned",0,H7*M7) -> 1365 | O7: =L7-N7 -> 996.7412 | P7: Completed
A8: =A7+1 -> 20250007 | B8: 45658 | C8: Jan | D8: Online | E8: Victoria Road 77 | F8: Lesley Wilson-Newman | G8: E-book | H8: 6 | I8: 9.71 | J8: =H8*I8 -> 58.26 | K8: 0.02 | L8: =IF(P8="Returned",0,J8*(1-K8)) -> 57.0948 | M8: 1 | N8: =IF(P8="Returned",0,H8*M8) -> 6 | O8: =L8-N8 -> 51.0948 | P8: Completed
A9: =A8+1 -> 20250008 | B9: 45658 | C9: Jan | D9: Online | E9: King Street 149 | F9: Albano Llopis Hierro | G9: Hardcover | H9: 13 | I9: 28.43 | J9: =H9*I9 -> 369.59 | K9: 0.03 | L9: =IF(P9="Returned",0,J9*(1-K9)) -> 358.5023 | M9: 15 | N9: =IF(P9="Returned",0,H9*M9) -> 195 | O9: =L9-N9 -> 163.5023 | P9: Completed
A10: =A9+1 -> 20250009 | B10: 45658 | C10: Jan | D10: Delivery | E10: King Street 151 | F10: Sra. Isabelly CâJana | G10: Paperback | H10: 28 | I10: 19.3 | J10: =H10*I10 -> 540.4 | K10: 0.08 | L10: =IF(P10="Returned",0,J10*(1-K10)) -> 497.168 | M10: 9.5 | N10: =IF(P10="Returned",0,H10*M10) -> 266 | O10: =L10-N10 -> 231.168 | P10: Completed
A11: =A10+1 -> 20250010 | B11: 45658 | C11: Jan | D11: Delivery | E11: Lake View Road 185 | F11: Abdul Hopkins | G11: Collector Edition | H11: 38 | I11: 42.88 | J11: =H11*I11 -> 1629.44 | K11: 0.08 | L11: =IF(P11="Returned",0,J11*(1-K11)) -> 1499.0848 | M11: 24 | N11: =IF(P11="Returned",0,H11*M11) -> 912 | O11: =L11-N11 -> 587.0848 | P11: Completed
A12: =A11+1 -> 20250011 | B12: 45658 | C12: Jan | D12: Online | E12: Garden Street 55 | F12: Cristian Santos | G12: Hardcover | H12: 22 | I12: 31.02 | J12: =H12*I12 -> 682.44 | K12: 0 | L12: =IF(P12="Returned",0,J12*(1-K12)) -> 682.44 | M12: 15 | N12: =IF(P12="Returned",0,H12*M12) -> 330 | O12: =L12-N12 -> 352.44 | P12: Completed
A13: =A12+1 -> 20250012 | B13: 45658 | C13: Jan | D13: Shop | E13: Park Avenue 122 | F13: Buenaventura de Bonet | G13: Collector Edition | H13: 22 | I13: 50.3 | J13: =H13*I13 -> 1106.6 | K13: 0.02 | L13: =IF(P13="Returned",0,J13*(1-K13)) -> 1084.468 | M13: 24 | N13: =IF(P13="Returned",0,H13*M13) -> 528 | O13: =L13-N13 -> 556.468 | P13: Completed
A14: =A13+1 -> 20250013 | B14: 45658 | C14: Jan | D14: Delivery | E14: River Street 206 | F14: Ileana Antón-Andrés | G14: Paperback | H14: 74 | I14: 17 | J14: =H14*I14 -> 1258 | K14: 0.15 | L14: =IF(P14="Returned",0,J14*(1-K14)) -> 1069.3 | M14: 9.5 | N14: =IF(P14="Returned",0,H14*M14) -> 703 | O14: =L14-N14 -> 366.3 | P14: Completed
... A511: =A510+1 -> 20250510 | B511: 45688 | C511: Jan | D511: Online | E511: Victoria Road 163 | F511: Deborah Figueroa | G511: Paperback | H511: 19 | I511: 20.21 | J511: =H511*I511 -> 383.99 | K511: 0.07 | L511: =IF(P511="Returned",0,J511*(1-K511)) -> 357.1107 | M511: 9.5 | N511: =IF(P511="Returned",0,H511*M511) -> 180.5 | O511: =L511-N511 -> 176.6107 | P511: Completed

Sheet Summary
A1: Business Sales Report
A3: Report Settings | I3: Key KPIs
A4: Currency | B4: USD | I4: Total Orders | J4: =SUM(B13:B24) -> 477
A5: Rows | B5: =J4 -> 477 | I5: Total Units | J5: =SUM(C13:C24) -> 10931
A6: Period | B6: 1 Month | I6: Total Net Sales (USD) | J6: =SUM(D13:D24) -> 199543.74
A7: Coverage | B7: 45658 | I7: Total Gross Profit (USD) | J7: =SUM(F13:F24) -> 100242.24
A8: Generated on | B8: 45691 | I8: Average Order Value (USD) | J8: =IFERROR(SUM(D13:D24)/SUM(B13:B24),0) -> 418.33069
I9: Gross Margin % | J9: =IFERROR(SUM(F13:F24)/SUM(D13:D24),0) -> 0.50235722
A11: Monthly Performance | I11: Sales by Channel
A12: Month | B12: Orders | C12: Units | D12: Net Sales (USD) | E12: COGS (USD) | F12: Gross Profit (USD) | G12: Gross Margin % | I12: Channel | J12: Net Sales (USD) | K12: Gross Profit (USD)
A13: Jan | B13: =COUNTIF('Sales Report'!$C$2:$C$478,A13) -> 477 | C13: =SUMIF('Sales Report'!$C$2:$C$478,A13,'Sales Report'!$H$2:$H$478) -> 10931 | D13: =SUMIF('Sales Report'!$C$2:$C$478,A13,'Sales Report'!$L$2:$L$478) -> 199543.74 | E13: =SUMIF('Sales Report'!$C$2:$C$478,A13,'Sales Report'!$N$2:$N$478) -> 99301.5 | F13: =D13-E13 -> 100242.24 | G13: =IFERROR(F13/D13,0) -> 0.50235722 | I13: Online | J13: =SUMIF('Sales Report'!$D$2:$D$478,I13,'Sales Report'!$L$2:$L$478) -> 45916.574 | K13: =SUMIF('Sales Report'!$D$2:$D$478,I13,'Sales Report'!$O$2:$O$478) -> 26538.574
A14: Feb | B14: =COUNTIF('Sales Report'!$C$2:$C$478,A14) -> 0 | C14: =SUMIF('Sales Report'!$C$2:$C$478,A14,'Sales Report'!$H$2:$H$478) -> 0 | D14: =SUMIF('Sales Report'!$C$2:$C$478,A14,'Sales Report'!$L$2:$L$478) -> 0 | E14: =SUMIF('Sales Report'!$C$2:$C$478,A14,'Sales Report'!$N$2:$N$478) -> 0 | F14: =D14-E14 -> 0 | G14: =IFERROR(F14/D14,0) -> 0 | I14: Shop | J14: =SUMIF('Sales Report'!$D$2:$D$478,I14,'Sales Report'!$L$2:$L$478) -> 26623.692 | K14: =SUMIF('Sales Report'!$D$2:$D$478,I14,'Sales Report'!$O$2:$O$478) -> 15463.692
A15: Mar | B15: =COUNTIF('Sales Report'!$C$2:$C$478,A15) -> 0 | C15: =SUMIF('Sales Report'!$C$2:$C$478,A15,'Sales Report'!$H$2:$H$478) -> 0 | D15: =SUMIF('Sales Report'!$C$2:$C$478,A15,'Sales Report'!$L$2:$L$478) -> 0 | E15: =SUMIF('Sales Report'!$C$2:$C$478,A15,'Sales Report'!$N$2:$N$478) -> 0 | F15: =D15-E15 -> 0 | G15: =IFERROR(F15/D15,0) -> 0 | I15: Delivery | J15: =SUMIF('Sales Report'!$D$2:$D$478,I15,'Sales Report'!$L$2:$L$478) -> 127003.47 | K15: =SUMIF('Sales Report'!$D$2:$D$478,I15,'Sales Report'!$O$2:$O$478) -> 58239.973
A16: Apr | B16: =COUNTIF('Sales Report'!$C$2:$C$478,A16) -> 0 | C16: =SUMIF('Sales Report'!$C$2:$C$478,A16,'Sales Report'!$H$2:$H$478) -> 0 | D16: =SUMIF('Sales Report'!$C$2:$C$478,A16,'Sales Report'!$L$2:$L$478) -> 0 | E16: =SUMIF('Sales Report'!$C$2:$C$478,A16,'Sales Report'!$N$2:$N$478) -> 0 | F16: =D16-E16 -> 0 | G16: =IFERROR(F16/D16,0) -> 0
A17: May | B17: =COUNTIF('Sales Report'!$C$2:$C$478,A17) -> 0 | C17: =SUMIF('Sales Report'!$C$2:$C$478,A17,'Sales Report'!$H$2:$H$478) -> 0 | D17: =SUMIF('Sales Report'!$C$2:$C$478,A17,'Sales Report'!$L$2:$L$478) -> 0 | E17: =SUMIF('Sales Report'!$C$2:$C$478,A17,'Sales Report'!$N$2:$N$478) -> 0 | F17: =D17-E17 -> 0 | G17: =IFERROR(F17/D17,0) -> 0
A18: Jun | B18: =COUNTIF('Sales Report'!$C$2:$C$478,A18) -> 0 | C18: =SUMIF('Sales Report'!$C$2:$C$478,A18,'Sales Report'!$H$2:$H$478) -> 0 | D18: =SUMIF('Sales Report'!$C$2:$C$478,A18,'Sales Report'!$L$2:$L$478) -> 0 | E18: =SUMIF('Sales Report'!$C$2:$C$478,A18,'Sales Report'!$N$2:$N$478) -> 0 | F18: =D18-E18 -> 0 | G18: =IFERROR(F18/D18,0) -> 0
A19: Jul | B19: =COUNTIF('Sales Report'!$C$2:$C$478,A19) -> 0 | C19: =SUMIF('Sales Report'!$C$2:$C$478,A19,'Sales Report'!$H$2:$H$478) -> 0 | D19: =SUMIF('Sales Report'!$C$2:$C$478,A19,'Sales Report'!$L$2:$L$478) -> 0 | E19: =SUMIF('Sales Report'!$C$2:$C$478,A19,'Sales Report'!$N$2:$N$478) -> 0 | F19: =D19-E19 -> 0 | G19: =IFERROR(F19/D19,0) -> 0
A20: Aug | B20: =COUNTIF('Sales Report'!$C$2:$C$478,A20) -> 0 | C20: =SUMIF('Sales Report'!$C$2:$C$478,A20,'Sales Report'!$H$2:$H$478) -> 0 | D20: =SUMIF('Sales Report'!$C$2:$C$478,A20,'Sales Report'!$L$2:$L$478) -> 0 | E20: =SUMIF('Sales Report'!$C$2:$C$478,A20,'Sales Report'!$N$2:$N$478) -> 0 | F20: =D20-E20 -> 0 | G20: =IFERROR(F20/D20,0) -> 0
A21: Sep | B21: =COUNTIF('Sales Report'!$C$2:$C$478,A21) -> 0 | C21: =SUMIF('Sales Report'!$C$2:$C$478,A21,'Sales Report'!$H$2:$H$478) -> 0 | D21: =SUMIF('Sales Report'!$C$2:$C$478,A21,'Sales Report'!$L$2:$L$478) -> 0 | E21: =SUMIF('Sales Report'!$C$2:$C$478,A21,'Sales Report'!$N$2:$N$478) -> 0 | F21: =D21-E21 -> 0 | G21: =IFERROR(F21/D21,0) -> 0
A22: Oct | B22: =COUNTIF('Sales Report'!$C$2:$C$478,A22) -> 0 | C22: =SUMIF('Sales Report'!$C$2:$C$478,A22,'Sales Report'!$H$2:$H$478) -> 0 | D22: =SUMIF('Sales Report'!$C$2:$C$478,A22,'Sales Report'!$L$2:$L$478) -> 0 | E22: =SUMIF('Sales Report'!$C$2:$C$478,A22,'Sales Report'!$N$2:$N$478) -> 0 | F22: =D22-E22 -> 0 | G22: =IFERROR(F22/D22,0) -> 0
A23: Nov | B23: =COUNTIF('Sales Report'!$C$2:$C$478,A23) -> 0 | C23: =SUMIF('Sales Report'!$C$2:$C$478,A23,'Sales Report'!$H$2:$H$478) -> 0 | D23: =SUMIF('Sales Report'!$C$2:$C$478,A23,'Sales Report'!$L$2:$L$478) -> 0 | E23: =SUMIF('Sales Report'!$C$2:$C$478,A23,'Sales Report'!$N$2:$N$478) -> 0 | F23: =D23-E23 -> 0 | G23: =IFERROR(F23/D23,0) -> 0
A24: Dec | B24: =COUNTIF('Sales Report'!$C$2:$C$478,A24) -> 0 | C24: =SUMIF('Sales Report'!$C$2:$C$478,A24,'Sales Report'!$H$2:$H$478) -> 0 | D24: =SUMIF('Sales Report'!$C$2:$C$478,A24,'Sales Report'!$L$2:$L$478) -> 0 | E24: =SUMIF('Sales Report'!$C$2:$C$478,A24,'Sales Report'!$N$2:$N$478) -> 0 | F24: =D24-E24 -> 0 | G24: =IFERROR(F24/D24,0) -> 0
A25: Total | B25: =SUM(B13:B24) -> 477 | C25: =SUM(C13:C24) -> 10931 | D25: =SUM(D13:D24) -> 199543.74 | E25: =SUM(E13:E24) -> 99301.5 | F25: =SUM(F13:F24) -> 100242.24 | G25: =IFERROR(F25/D25,0) -> 0.50235722
